la_rag/__init__.py
la_rag/__main__.py
la_rag/documentClass.py
la_rag/layout_parser.py
la_rag/pipeline.py
la_rag/postprocessor.py
la_rag/preprocessor.py
la_rag-0.1.5.dist-info/LICENSE
la_rag-0.1.5.dist-info/METADATA
la_rag-0.1.5.dist-info/WHEEL
la_rag-0.1.5.dist-info/top_level.txt
la_rag-0.1.5.dist-info/RECORD
