Metadata-Version: 2.1
Name: la-rag
Version: 0.1.5
Summary: Layout Aware RAG
Home-page: https://github.com/MuafiraThasni/LayoutAwareRAG
Author: Muafira
Author-email: muafirathasnikt@gmail.com
Classifier: Programming Language :: Python :: 3
Classifier: License :: OSI Approved :: MIT License
Classifier: Operating System :: OS Independent
Requires-Python: >=3.11
License-File: LICENSE
Requires-Dist: nltk
Requires-Dist: transformers
Requires-Dist: torch
